ocrhelper/__init__.py
ocrhelper/app.py
ocrhelper/components/__init__.py
ocrhelper/components/config.py
ocrhelper/components/languages.py
ocrhelper/components/translation.py
ocrhelper/components/utils.py
ocrhelper/gui.py
ocrhelper/gui_parts/__init__.py
ocrhelper/gui_parts/animation.py
ocrhelper/gui_parts/debug_window.py
ocrhelper/gui_parts/gui_settings.py
ocrhelper/gui_parts/main_window_frame.py
ocrhelper/gui_parts/settings_parts/__init__.py
ocrhelper/gui_parts/settings_parts/api_dialog_gui.py
ocrhelper/gui_parts/settings_parts/language_frames.py
ocrhelper/gui_parts/settings_parts/options_gui.py
ocrhelper/gui_parts/settings_parts/palette_gui.py
ocrhelper/gui_parts/settings_parts/segmented_gui.py
ocrhelper/gui_parts/snip.py
ocrhelper/gui_parts/toast.py
ocrhelper/ocr.py
ocrhelper/result_window.py
ocrhelper-1.2.1.dist-info/LICENSE.md
ocrhelper-1.2.1.dist-info/METADATA
ocrhelper-1.2.1.dist-info/WHEEL
ocrhelper-1.2.1.dist-info/RECORD
