Metadata-Version: 2.1
Name: ocrhelper
Version: 1.2.1
Summary: Tool for translating text from the screen and some more
Author: Sergei
Author-email: reyangood@gmail.com
Requires-Python: >=3.11,<4.0
Classifier: Programming Language :: Python :: 3
Classifier: Programming Language :: Python :: 3.11
Classifier: Programming Language :: Python :: 3.12
Requires-Dist: ctkmessagebox (>=2.5,<3.0)
Requires-Dist: customtkinter (>=5.2.1,<6.0.0)
Requires-Dist: deep-translator[ai] (>=1.11.4,<2.0.0)
Requires-Dist: keyboard (>=0.13.5,<0.14.0)
Requires-Dist: keyring (>=24.3.0,<25.0.0)
Requires-Dist: numpy (>=1.25.1,<2.0.0)
Requires-Dist: pillow (==9.5.0)
Requires-Dist: pyperclip (>=1.8.2,<2.0.0)
Requires-Dist: pystray (>=0.19.4,<0.20.0)
